[
    {
        "id": 1,
        "titulo": "añljsdlñaj",
        "descripcion": "lñasdñlajsñdlas",
        "color": "#000000",
        "image": "image-1621808109817.jpg"
    },
    {
        "id": 2,
        "titulo": "añlksdñlaksdas",
        "descripcion": "alkdañsldas",
        "color": "#73ff00",
        "image": "image-1621808135112.jpg"
    },
    {
        "id": 3,
        "titulo": "lañdjañlsdja",
        "descripcion": "ñlasñldjañlsdas",
        "color": "#c24747",
        "image": "image-1621808166555.jpg"
    }
]